debug_toolz/__init__.py
debug_toolz/base.py
debug_toolz-0.0.1.dist-info/DESCRIPTION.rst
debug_toolz-0.0.1.dist-info/METADATA
debug_toolz-0.0.1.dist-info/RECORD
debug_toolz-0.0.1.dist-info/WHEEL
debug_toolz-0.0.1.dist-info/metadata.json
debug_toolz-0.0.1.dist-info/top_level.txt
