Metadata-Version: 2.0
Name: debug-toolz
Version: 0.0.1
Summary: Tools to ease debugging
Home-page: https://github.com/jakab922/debug_toolz
Author: Daniel Papp
Author-email: jakab922@gmail.com
License: MIT
Download-URL: https://github.com/jakab922/debug_toolz/tarball/0.0.1
Keywords: debug tooling
Platform: UNKNOWN
Classifier: Development Status :: 3 - Alpha
Classifier: License :: OSI Approved :: MIT License
Classifier: Programming Language :: Python :: 2.7
Requires-Dist: toolz (==0.9.0)
